ynlu/__init__.py
ynlu/__version__.py
ynlu/exceptions.py
ynlu/intent_classifier/__init__.py
ynlu/intent_classifier/client.py
ynlu/intent_classifier/global_variables.py
ynlu/intent_classifier/test/__init__.py
ynlu/intent_classifier/test/test_client.py
ynlu/sdk/__init__.py
ynlu/sdk/client.py
ynlu/sdk/exceptions.py
ynlu/sdk/model.py
ynlu/sdk/evaluation/__init__.py
ynlu/sdk/evaluation/entity_confusion_matrix.py
ynlu/sdk/evaluation/entity_overlapping_score.py
ynlu/sdk/evaluation/exceptions.py
ynlu/sdk/evaluation/intent_accuracy_score_with_threshold.py
ynlu/sdk/evaluation/intent_precision_recall.py
ynlu/sdk/evaluation/intent_precision_score_with_threshold.py
ynlu/sdk/evaluation/intent_recall_score_with_threshold.py
ynlu/sdk/evaluation/intent_topk_accuracy_score.py
ynlu/sdk/evaluation/intent_topk_precision_score.py
ynlu/sdk/evaluation/intent_topk_recall_score.py
ynlu/sdk/evaluation/utils.py
ynlu/sdk/evaluation/plot/__init__.py
ynlu/sdk/evaluation/plot/confusion_matrix_plot.py
ynlu/sdk/evaluation/plot/line_plot.py
ynlu/sdk/evaluation/plot/utils.py
ynlu/sdk/evaluation/plot/test/__init__.py
ynlu/sdk/evaluation/plot/test/test_confusion_matrix_plot.py
ynlu/sdk/evaluation/plot/test/test_line_plot.py
ynlu/sdk/evaluation/tests/__init__.py
ynlu/sdk/evaluation/tests/test_entity_confusion_matrix.py
ynlu/sdk/evaluation/tests/test_entity_overlapping_ratio.py
ynlu/sdk/evaluation/tests/test_intent_accuracy_score_with_threshold.py
ynlu/sdk/evaluation/tests/test_intent_precision_recall.py
ynlu/sdk/evaluation/tests/test_intent_precision_score_with_threshold.py
ynlu/sdk/evaluation/tests/test_intent_recall_score_with_threshold.py
ynlu/sdk/evaluation/tests/test_intent_topk_accuracy_score.py
ynlu/sdk/evaluation/tests/test_intent_topk_precision_score.py
ynlu/sdk/evaluation/tests/test_intent_topk_recall_score.py
ynlu/sdk/evaluation/tests/test_utils.py
ynlu/sdk/test/__init__.py
ynlu/sdk/test/test_client.py
ynlu/sdk/test/test_model.py
yoctol_nlu-0.7.1.dist-info/DESCRIPTION.rst
yoctol_nlu-0.7.1.dist-info/METADATA
yoctol_nlu-0.7.1.dist-info/RECORD
yoctol_nlu-0.7.1.dist-info/WHEEL
yoctol_nlu-0.7.1.dist-info/metadata.json
yoctol_nlu-0.7.1.dist-info/top_level.txt
