Metadata-Version: 2.0
Name: yoctol-nlu
Version: 0.7.1
Summary: Yoctol Natural Language Understanding SDK
Home-page: UNKNOWN
Author: cph
Author-email: UNKNOWN
License: MIT
Platform: UNKNOWN
Classifier: Programming Language :: Python
Classifier: Programming Language :: Python :: 3.6
Requires-Dist: gql-fork (>=0.2.0)
Requires-Dist: requests (>=2.13.0)
Requires-Dist: scipy (>=1.0.1)
Requires-Dist: numpy (>=1.14.2)
Requires-Dist: matplotlib (==2.2.2)
Requires-Dist: pandas
Requires-Dist: pandas (<0.21)
Requires-Dist: seaborn (>=0.8.1)
Requires-Dist: scikit-learn (>=0.19.1)
